gllm_agents.cpython-311-darwin.so
gllm_agents.pyi
gllm_agents/__init__.pyi
gllm_agents/constants.pyi
gllm_agents/a2a/__init__.pyi
gllm_agents/a2a/types.pyi
gllm_agents/a2a/server/__init__.pyi
gllm_agents/a2a/server/base_executor.pyi
gllm_agents/a2a/server/google_adk_executor.pyi
gllm_agents/a2a/server/langflow_executor.pyi
gllm_agents/a2a/server/langgraph_executor.pyi
gllm_agents/agent/__init__.pyi
gllm_agents/agent/base_agent.pyi
gllm_agents/agent/base_langgraph_agent.pyi
gllm_agents/agent/google_adk_agent.pyi
gllm_agents/agent/interface.pyi
gllm_agents/agent/langflow_agent.pyi
gllm_agents/agent/langgraph_react_agent.pyi
gllm_agents/agent/recall_agent.pyi
gllm_agents/agent/system_instruction_context.pyi
gllm_agents/agent/hitl/__init__.pyi
gllm_agents/agent/hitl/config.pyi
gllm_agents/agent/hitl/langgraph_hitl_mixin.pyi
gllm_agents/agent/hitl/manager.pyi
gllm_agents/agent/hitl/models.pyi
gllm_agents/agent/hitl/prompt/__init__.pyi
gllm_agents/agent/hitl/prompt/base.pyi
gllm_agents/agent/hitl/prompt/deferred.pyi
gllm_agents/clients/__init__.pyi
gllm_agents/clients/langflow/__init__.pyi
gllm_agents/clients/langflow/client.pyi
gllm_agents/clients/langflow/types.pyi
gllm_agents/examples/__init__.pyi
gllm_agents/examples/demo_memory_recall.pyi
gllm_agents/examples/hello_world_a2a_google_adk_client.pyi
gllm_agents/examples/hello_world_a2a_google_adk_client_agent.pyi
gllm_agents/examples/hello_world_a2a_google_adk_client_streaming.pyi
gllm_agents/examples/hello_world_a2a_google_adk_server.pyi
gllm_agents/examples/hello_world_a2a_langchain_client.pyi
gllm_agents/examples/hello_world_a2a_langchain_client_agent.pyi
gllm_agents/examples/hello_world_a2a_langchain_client_lm_invoker.pyi
gllm_agents/examples/hello_world_a2a_langchain_client_streaming.pyi
gllm_agents/examples/hello_world_a2a_langchain_reference_client_streaming.pyi
gllm_agents/examples/hello_world_a2a_langchain_reference_server.pyi
gllm_agents/examples/hello_world_a2a_langchain_server.pyi
gllm_agents_binary-0.4.25.dist-info/METADATA
gllm_agents_binary-0.4.25.dist-info/WHEEL
gllm_agents_binary-0.4.25.dist-info/top_level.txt
gllm_agents_binary-0.4.25.dist-info/RECORD
