Metadata-Version: 2.2
Name: gllm-agents-binary
Version: 0.4.25
Summary: A library for managing agents in Gen AI applications.
Author-email: Raymond Christopher <raymond.christopher@gdplabs.id>
Requires-Python: <3.14,>=3.11
Requires-Dist: a2a-sdk<0.2.12,>=0.2.4
Requires-Dist: bosa-connectors-binary<0.3.0,>=0.2.2
Requires-Dist: bosa-core-binary[logger,telemetry]<0.10.0,>=0.9.0
Requires-Dist: colorama<0.5.0,>=0.4.6
Requires-Dist: deprecated<2.0.0,>=1.2.18
Requires-Dist: fastapi<0.118.0,>=0.117.0
Requires-Dist: gllm-core-binary<0.4.0,>=0.3.0
Requires-Dist: gllm-inference-binary[anthropic,bedrock,google-genai,google-vertexai,openai]<0.6.0,>=0.5.0
Requires-Dist: gllm-tools-binary<0.2.0,>=0.1.1
Requires-Dist: google-adk<0.6.0,>=0.5.0
Requires-Dist: langchain<0.4.0,>=0.3.0
Requires-Dist: langchain-openai<0.4.0,>=0.3.17
Requires-Dist: langgraph<0.3.0,>=0.2.16
Requires-Dist: mem0ai<0.2.0,>=0.1.115
Requires-Dist: minio<8.0.0,>=7.2.16
Requires-Dist: pydantic<3.0.0,>=2.9.1
Requires-Dist: python-dotenv<2.0.0,>=1.0.0
Requires-Dist: requests<3.0.0,>=2.32.4
Requires-Dist: uvicorn<0.35.0,>=0.34.0
Requires-Dist: authlib<1.7.0,>=1.6.4
Requires-Dist: aiostream<0.8.0,>=0.6.0
Provides-Extra: dev
Requires-Dist: coverage<8.0.0,>=7.4.4; extra == "dev"
Requires-Dist: mypy<2.0.0,>=1.15.0; extra == "dev"
Requires-Dist: pre-commit<4.0.0,>=3.7.0; extra == "dev"
Requires-Dist: pytest<9.0.0,>=8.1.1; extra == "dev"
Requires-Dist: pytest-asyncio<0.24.0,>=0.23.6; extra == "dev"
Requires-Dist: pytest-cov<6.0.0,>=5.0.0; extra == "dev"
Requires-Dist: ruff<0.7.0,>=0.6.7; extra == "dev"
Requires-Dist: pillow<12.0.0,>=11.3.0; extra == "dev"
